sigma_16p.v
//2022-7-31.罗力中；
//相邻16点相加；目的是用累加器实现乘法运算。比如16程以某个数。

module sigma_16p(
		clk,
		res,
		data_in,
		syn_in,
		data_out,
		syn_out
		);
input		clk;
input		res;
input[7:0]		data_in;//采样数据
input			syn_in;//采样时钟；
output[11:0]		data_out;//累加和；
output			syn_out;//累加和同步脉冲；

reg		syn_in_n1;//syn_in的反向延时；
wire		syn_pulse;//采样时钟上升沿识别脉冲；
assign		syn_pulse=syn_in&syn_in_n1;

reg[3:0]	con_syn;//脉冲尖循环计数；
wire[7:0]	comp_8;//补码；
wire[6:0]	comp_7;//反码+1；
wire[11:0]	d_12;//升码；

/*assign comp_8=data_in[7]?{data_in[7],~data_in[6:0]+1}:data_in;//求补码；*/
assign comp_7=~data_in[6:0]+1;//反码+1;
assign comp_8=data_in[7]?{data_in[7],comp_7}:data_in;//间接求补码；
assign d_12={comp_8[7],comp_8[7],comp_8[7],comp_8[7],comp_8};

reg[11:0]	sigma;//累加计算；
reg[11:0]	data_out;//累加和；
reg		syn_out;//累加和同步脉冲；

always@(posedge clk or negedge res) begin
if(~res) begin
	syn_in_n1<=0;con_syn<=0;sigma<=0;data_out<=0;syn_out<=0;
end
else begin
	syn_in_n1<=~syn_in;
	
	if(syn_pulse==1) begin
	con_syn<=con_syn+1;
	end

	if(syn_pulse==1)begin
		if(con_syn==15) begin
		sigma<=d_12;
		data_out<=sigma;
		syn_out<=1;
		end
		else begin
		sigma<=sigma+d_12;
		end
	end
	else begin
	syn_out<=0;
	end
   end
end



endmodule

sigma_16p_tb.v
//----testbench of sigma_16p-----

`timescale 1ns/10ps
module sigma_16p_tb;
reg		clk,res;
reg[7:0]	data_in;
reg		syn_in;
wire[11:0]	data_out;
wire		syn_out;

sigma_16p sigma_16p(
		.clk(clk),
		.res(res),
		.data_in(data_in),
		.syn_in(syn_in),
		.data_out(data_out),
		.syn_out(syn_out)
		);
initial begin
	clk<=0;res<=0;data_in<=8'b0000_0010;;syn_in<=0;//data_in<=8'b1000_0001表示负1；
	#17 res<=1;
	#25000 $stop;
end

always #5 clk=~clk;

always #100 syn_in=~syn_in;

initial begin
	$dumpfile("test11-2.vcd");
	$dumpvars(0,sigma_16p_tb);
end


endmodule

test11-2.vcd
$date
	Sat Jul 30 22:18:48 2022
$end
$version
	Icarus Verilog
$end
$timescale
	10ps
$end
$scope module sigma_16p_tb $end
$var wire 1 ! syn_out $end
$var wire 12 " data_out [11:0] $end
$var reg 1 # clk $end
$var reg 8 $ data_in [7:0] $end
$var reg 1 % res $end
$var reg 1 & syn_in $end
$scope module sigma_16p $end
$var wire 1 # clk $end
$var wire 8 ' data_in [7:0] $end
$var wire 1 % res $end
$var wire 1 & syn_in $end
$var wire 1 ( syn_pulse $end
$var wire 12 ) d_12 [11:0] $end
$var wire 8 * comp_8 [7:0] $end
$var wire 7 + comp_7 [6:0] $end
$var reg 4 , con_syn [3:0] $end
$var reg 12 - data_out [11:0] $end
$var reg 12 . sigma [11:0] $end
$var reg 1 / syn_in_n1 $end
$var reg 1 ! syn_out $end
$upscope $end
$upscope $end
$enddefinitions $end
$comment Show the parameter values. $end
$dumpall
$end
#0
$dumpvars
0/
b0 .
b0 -
b0 ,
b1111110 +
b10 *
b10 )
0(
b10 '
0&
0%
b10 $
0#
b0 "
0!
$end
#500
1#
#1000
0#
#1500
1#
#1700
1%
#2000
0#
#2500
1/
1#
#3000
0#
#3500
1#
#4000
0#
#4500
1#
#5000
0#
#5500
1#
#6000
0#
#6500
1#
#7000
0#
#7500
1#
#8000
0#
#8500
1#
#9000
0#
#9500
1#
#10000
1(
0#
1&
#10500
0(
b10 .
b1 ,
0/
1#
#11000
0#
#11500
1#
#12000
0#
#12500
1#
#13000
0#
#13500
1#
#14000
0#
#14500
1#
#15000
0#
#15500
1#
#16000
0#
#16500
1#
#17000
0#
#17500
1#
#18000
0#
#18500
1#
#19000
0#
#19500
1#
#20000
0#
0&
#20500
1/
1#
#21000
0#
#21500
1#
#22000
0#
#22500
1#
#23000
0#
#23500
1#
#24000
0#
#24500
1#
#25000
0#
#25500
1#
#26000
0#
#26500
1#
#27000
0#
#27500
1#
#28000
0#
#28500
1#
#29000
0#
#29500
1#
#30000
1(
0#
1&
#30500
0(
b100 .
b10 ,
0/
1#
#31000
0#
#31500
1#
#32000
0#
#32500
1#
#33000
0#
#33500
1#
#34000
0#
#34500
1#
#35000
0#
#35500
1#
#36000
0#
#36500
1#
#37000
0#
#37500
1#
#38000
0#
#38500
1#
#39000
0#
#39500
1#
#40000
0#
0&
#40500
1/
1#
#41000
0#
#41500
1#
#42000
0#
#42500
1#
#43000
0#
#43500
1#
#44000
0#
#44500
1#
#45000
0#
#45500
1#
#46000
0#
#46500
1#
#47000
0#
#47500
1#
#48000
0#
#48500
1#
#49000
0#
#49500
1#
#50000
1(
0#
1&
#50500
0(
b110 .
b11 ,
0/
1#
#51000
0#
#51500
1#
#52000
0#
#52500
1#
#53000
0#
#53500
1#
#54000
0#
#54500
1#
#55000
0#
#55500
1#
#56000
0#
#56500
1#
#57000
0#
#57500
1#
#58000
0#
#58500
1#
#59000
0#
#59500
1#
#60000
0#
0&
#60500
1/
1#
#61000
0#
#61500
1#
#62000
0#
#62500
1#
#63000
0#
#63500
1#
#64000
0#
#64500
1#
#65000
0#
#65500
1#
#66000
0#
#66500
1#
#67000
0#
#67500
1#
#68000
0#
#68500
1#
#69000
0#
#69500
1#
#70000
1(
0#
1&
#70500
0(
b1000 .
b100 ,
0/
1#
#71000
0#
#71500
1#
#72000
0#
#72500
1#
#73000
0#
#73500
1#
#74000
0#
#74500
1#
#75000
0#
#75500
1#
#76000
0#
#76500
1#
#77000
0#
#77500
1#
#78000
0#
#78500
1#
#79000
0#
#79500
1#
#80000
0#
0&
#80500
1/
1#
#81000
0#
#81500
1#
#82000
0#
#82500
1#
#83000
0#
#83500
1#
#84000
0#
#84500
1#
#85000
0#
#85500
1#
#86000
0#
#86500
1#
#87000
0#
#87500
1#
#88000
0#
#88500
1#
#89000
0#
#89500
1#
#90000
1(
0#
1&
#90500
0(
b1010 .
b101 ,
0/
1#
#91000
0#
#91500
1#
#92000
0#
#92500
1#
#93000
0#
#93500
1#
#94000
0#
#94500
1#
#95000
0#
#95500
1#
#96000
0#
#96500
1#
#97000
0#
#97500
1#
#98000
0#
#98500
1#
#99000
0#
#99500
1#
#100000
0#
0&
#100500
1/
1#
#101000
0#
#101500
1#
#102000
0#
#102500
1#
#103000
0#
#103500
1#
#104000
0#
#104500
1#
#105000
0#
#105500
1#
#106000
0#
#106500
1#
#107000
0#
#107500
1#
#108000
0#
#108500
1#
#109000
0#
#109500
1#
#110000
1(
0#
1&
#110500
0(
b1100 .
b110 ,
0/
1#
#111000
0#
#111500
1#
#112000
0#
#112500
1#
#113000
0#
#113500
1#
#114000
0#
#114500
1#
#115000
0#
#115500
1#
#116000
0#
#116500
1#
#117000
0#
#117500
1#
#118000
0#
#118500
1#
#119000
0#
#119500
1#
#120000
0#
0&
#120500
1/
1#
#121000
0#
#121500
1#
#122000
0#
#122500
1#
#123000
0#
#123500
1#
#124000
0#
#124500
1#
#125000
0#
#125500
1#
#126000
0#
#126500
1#
#127000
0#
#127500
1#
#128000
0#
#128500
1#
#129000
0#
#129500
1#
#130000
1(
0#
1&
#130500
0(
b1110 .
b111 ,
0/
1#
#131000
0#
#131500
1#
#132000
0#
#132500
1#
#133000
0#
#133500
1#
#134000
0#
#134500
1#
#135000
0#
#135500
1#
#136000
0#
#136500
1#
#137000
0#
#137500
1#
#138000
0#
#138500
1#
#139000
0#
#139500
1#
#140000
0#
0&
#140500
1/
1#
#141000
0#
#141500
1#
#142000
0#
#142500
1#
#143000
0#
#143500
1#
#144000
0#
#144500
1#
#145000
0#
#145500
1#
#146000
0#
#146500
1#
#147000
0#
#147500
1#
#148000
0#
#148500
1#
#149000
0#
#149500
1#
#150000
1(
0#
1&
#150500
0(
b10000 .
b1000 ,
0/
1#
#151000
0#
#151500
1#
#152000
0#
#152500
1#
#153000
0#
#153500
1#
#154000
0#
#154500
1#
#155000
0#
#155500
1#
#156000
0#
#156500
1#
#157000
0#
#157500
1#
#158000
0#
#158500
1#
#159000
0#
#159500
1#
#160000
0#
0&
#160500
1/
1#
#161000
0#
#161500
1#
#162000
0#
#162500
1#
#163000
0#
#163500
1#
#164000
0#
#164500
1#
#165000
0#
#165500
1#
#166000
0#
#166500
1#
#167000
0#
#167500
1#
#168000
0#
#168500
1#
#169000
0#
#169500
1#
#170000
1(
0#
1&
#170500
0(
b10010 .
b1001 ,
0/
1#
#171000
0#
#171500
1#
#172000
0#
#172500
1#
#173000
0#
#173500
1#
#174000
0#
#174500
1#
#175000
0#
#175500
1#
#176000
0#
#176500
1#
#177000
0#
#177500
1#
#178000
0#
#178500
1#
#179000
0#
#179500
1#
#180000
0#
0&
#180500
1/
1#
#181000
0#
#181500
1#
#182000
0#
#182500
1#
#183000
0#
#183500
1#
#184000
0#
#184500
1#
#185000
0#
#185500
1#
#186000
0#
#186500
1#
#187000
0#
#187500
1#
#188000
0#
#188500
1#
#189000
0#
#189500
1#
#190000
1(
0#
1&
#190500
0(
b10100 .
b1010 ,
0/
1#
#191000
0#
#191500
1#
#192000
0#
#192500
1#
#193000
0#
#193500
1#
#194000
0#
#194500
1#
#195000
0#
#195500
1#
#196000
0#
#196500
1#
#197000
0#
#197500
1#
#198000
0#
#198500
1#
#199000
0#
#199500
1#
#200000
0#
0&
#200500
1/
1#
#201000
0#
#201500
1#
#202000
0#
#202500
1#
#203000
0#
#203500
1#
#204000
0#
#204500
1#
#205000
0#
#205500
1#
#206000
0#
#206500
1#
#207000
0#
#207500
1#
#208000
0#
#208500
1#
#209000
0#
#209500
1#
#210000
1(
0#
1&
#210500
0(
b10110 .
b1011 ,
0/
1#
#211000
0#
#211500
1#
#212000
0#
#212500
1#
#213000
0#
#213500
1#
#214000
0#
#214500
1#
#215000
0#
#215500
1#
#216000
0#
#216500
1#
#217000
0#
#217500
1#
#218000
0#
#218500
1#
#219000
0#
#219500
1#
#220000
0#
0&
#220500
1/
1#
#221000
0#
#221500
1#
#222000
0#
#222500
1#
#223000
0#
#223500
1#
#224000
0#
#224500
1#
#225000
0#
#225500
1#
#226000
0#
#226500
1#
#227000
0#
#227500
1#
#228000
0#
#228500
1#
#229000
0#
#229500
1#
#230000
1(
0#
1&
#230500
0(
b11000 .
b1100 ,
0/
1#
#231000
0#
#231500
1#
#232000
0#
#232500
1#
#233000
0#
#233500
1#
#234000
0#
#234500
1#
#235000
0#
#235500
1#
#236000
0#
#236500
1#
#237000
0#
#237500
1#
#238000
0#
#238500
1#
#239000
0#
#239500
1#
#240000
0#
0&
#240500
1/
1#
#241000
0#
#241500
1#
#242000
0#
#242500
1#
#243000
0#
#243500
1#
#244000
0#
#244500
1#
#245000
0#
#245500
1#
#246000
0#
#246500
1#
#247000
0#
#247500
1#
#248000
0#
#248500
1#
#249000
0#
#249500
1#
#250000
1(
0#
1&
#250500
0(
b11010 .
b1101 ,
0/
1#
#251000
0#
#251500
1#
#252000
0#
#252500
1#
#253000
0#
#253500
1#
#254000
0#
#254500
1#
#255000
0#
#255500
1#
#256000
0#
#256500
1#
#257000
0#
#257500
1#
#258000
0#
#258500
1#
#259000
0#
#259500
1#
#260000
0#
0&
#260500
1/
1#
#261000
0#
#261500
1#
#262000
0#
#262500
1#
#263000
0#
#263500
1#
#264000
0#
#264500
1#
#265000
0#
#265500
1#
#266000
0#
#266500
1#
#267000
0#
#267500
1#
#268000
0#
#268500
1#
#269000
0#
#269500
1#
#270000
1(
0#
1&
#270500
0(
b11100 .
b1110 ,
0/
1#
#271000
0#
#271500
1#
#272000
0#
#272500
1#
#273000
0#
#273500
1#
#274000
0#
#274500
1#
#275000
0#
#275500
1#
#276000
0#
#276500
1#
#277000
0#
#277500
1#
#278000
0#
#278500
1#
#279000
0#
#279500
1#
#280000
0#
0&
#280500
1/
1#
#281000
0#
#281500
1#
#282000
0#
#282500
1#
#283000
0#
#283500
1#
#284000
0#
#284500
1#
#285000
0#
#285500
1#
#286000
0#
#286500
1#
#287000
0#
#287500
1#
#288000
0#
#288500
1#
#289000
0#
#289500
1#
#290000
1(
0#
1&
#290500
0(
b11110 .
b1111 ,
0/
1#
#291000
0#
#291500
1#
#292000
0#
#292500
1#
#293000
0#
#293500
1#
#294000
0#
#294500
1#
#295000
0#
#295500
1#
#296000
0#
#296500
1#
#297000
0#
#297500
1#
#298000
0#
#298500
1#
#299000
0#
#299500
1#
#300000
0#
0&
#300500
1/
1#
#301000
0#
#301500
1#
#302000
0#
#302500
1#
#303000
0#
#303500
1#
#304000
0#
#304500
1#
#305000
0#
#305500
1#
#306000
0#
#306500
1#
#307000
0#
#307500
1#
#308000
0#
#308500
1#
#309000
0#
#309500
1#
#310000
1(
0#
1&
#310500
0(
1!
b11110 "
b11110 -
b10 .
b0 ,
0/
1#
#311000
0#
#311500
0!
1#
#312000
0#
#312500
1#
#313000
0#
#313500
1#
#314000
0#
#314500
1#
#315000
0#
#315500
1#
#316000
0#
#316500
1#
#317000
0#
#317500
1#
#318000
0#
#318500
1#
#319000
0#
#319500
1#
#320000
0#
0&
#320500
1/
1#
#321000
0#
#321500
1#
#322000
0#
#322500
1#
#323000
0#
#323500
1#
#324000
0#
#324500
1#
#325000
0#
#325500
1#
#326000
0#
#326500
1#
#327000
0#
#327500
1#
#328000
0#
#328500
1#
#329000
0#
#329500
1#
#330000
1(
0#
1&
#330500
0(
b100 .
b1 ,
0/
1#
#331000
0#
#331500
1#
#332000
0#
#332500
1#
#333000
0#
#333500
1#
#334000
0#
#334500
1#
#335000
0#
#335500
1#
#336000
0#
#336500
1#
#337000
0#
#337500
1#
#338000
0#
#338500
1#
#339000
0#
#339500
1#
#340000
0#
0&
#340500
1/
1#
#341000
0#
#341500
1#
#342000
0#
#342500
1#
#343000
0#
#343500
1#
#344000
0#
#344500
1#
#345000
0#
#345500
1#
#346000
0#
#346500
1#
#347000
0#
#347500
1#
#348000
0#
#348500
1#
#349000
0#
#349500
1#
#350000
1(
0#
1&
#350500
0(
b110 .
b10 ,
0/
1#
#351000
0#
#351500
1#
#352000
0#
#352500
1#
#353000
0#
#353500
1#
#354000
0#
#354500
1#
#355000
0#
#355500
1#
#356000
0#
#356500
1#
#357000
0#
#357500
1#
#358000
0#
#358500
1#
#359000
0#
#359500
1#
#360000
0#
0&
#360500
1/
1#
#361000
0#
#361500
1#
#362000
0#
#362500
1#
#363000
0#
#363500
1#
#364000
0#
#364500
1#
#365000
0#
#365500
1#
#366000
0#
#366500
1#
#367000
0#
#367500
1#
#368000
0#
#368500
1#
#369000
0#
#369500
1#
#370000
1(
0#
1&
#370500
0(
b1000 .
b11 ,
0/
1#
#371000
0#
#371500
1#
#372000
0#
#372500
1#
#373000
0#
#373500
1#
#374000
0#
#374500
1#
#375000
0#
#375500
1#
#376000
0#
#376500
1#
#377000
0#
#377500
1#
#378000
0#
#378500
1#
#379000
0#
#379500
1#
#380000
0#
0&
#380500
1/
1#
#381000
0#
#381500
1#
#382000
0#
#382500
1#
#383000
0#
#383500
1#
#384000
0#
#384500
1#
#385000
0#
#385500
1#
#386000
0#
#386500
1#
#387000
0#
#387500
1#
#388000
0#
#388500
1#
#389000
0#
#389500
1#
#390000
1(
0#
1&
#390500
0(
b1010 .
b100 ,
0/
1#
#391000
0#
#391500
1#
#392000
0#
#392500
1#
#393000
0#
#393500
1#
#394000
0#
#394500
1#
#395000
0#
#395500
1#
#396000
0#
#396500
1#
#397000
0#
#397500
1#
#398000
0#
#398500
1#
#399000
0#
#399500
1#
#400000
0#
0&
#400500
1/
1#
#401000
0#
#401500
1#
#402000
0#
#402500
1#
#403000
0#
#403500
1#
#404000
0#
#404500
1#
#405000
0#
#405500
1#
#406000
0#
#406500
1#
#407000
0#
#407500
1#
#408000
0#
#408500
1#
#409000
0#
#409500
1#
#410000
1(
0#
1&
#410500
0(
b1100 .
b101 ,
0/
1#
#411000
0#
#411500
1#
#412000
0#
#412500
1#
#413000
0#
#413500
1#
#414000
0#
#414500
1#
#415000
0#
#415500
1#
#416000
0#
#416500
1#
#417000
0#
#417500
1#
#418000
0#
#418500
1#
#419000
0#
#419500
1#
#420000
0#
0&
#420500
1/
1#
#421000
0#
#421500
1#
#422000
0#
#422500
1#
#423000
0#
#423500
1#
#424000
0#
#424500
1#
#425000
0#
#425500
1#
#426000
0#
#426500
1#
#427000
0#
#427500
1#
#428000
0#
#428500
1#
#429000
0#
#429500
1#
#430000
1(
0#
1&
#430500
0(
b1110 .
b110 ,
0/
1#
#431000
0#
#431500
1#
#432000
0#
#432500
1#
#433000
0#
#433500
1#
#434000
0#
#434500
1#
#435000
0#
#435500
1#
#436000
0#
#436500
1#
#437000
0#
#437500
1#
#438000
0#
#438500
1#
#439000
0#
#439500
1#
#440000
0#
0&
#440500
1/
1#
#441000
0#
#441500
1#
#442000
0#
#442500
1#
#443000
0#
#443500
1#
#444000
0#
#444500
1#
#445000
0#
#445500
1#
#446000
0#
#446500
1#
#447000
0#
#447500
1#
#448000
0#
#448500
1#
#449000
0#
#449500
1#
#450000
1(
0#
1&
#450500
0(
b10000 .
b111 ,
0/
1#
#451000
0#
#451500
1#
#452000
0#
#452500
1#
#453000
0#
#453500
1#
#454000
0#
#454500
1#
#455000
0#
#455500
1#
#456000
0#
#456500
1#
#457000
0#
#457500
1#
#458000
0#
#458500
1#
#459000
0#
#459500
1#
#460000
0#
0&
#460500
1/
1#
#461000
0#
#461500
1#
#462000
0#
#462500
1#
#463000
0#
#463500
1#
#464000
0#
#464500
1#
#465000
0#
#465500
1#
#466000
0#
#466500
1#
#467000
0#
#467500
1#
#468000
0#
#468500
1#
#469000
0#
#469500
1#
#470000
1(
0#
1&
#470500
0(
b10010 .
b1000 ,
0/
1#
#471000
0#
#471500
1#
#472000
0#
#472500
1#
#473000
0#
#473500
1#
#474000
0#
#474500
1#
#475000
0#
#475500
1#
#476000
0#
#476500
1#
#477000
0#
#477500
1#
#478000
0#
#478500
1#
#479000
0#
#479500
1#
#480000
0#
0&
#480500
1/
1#
#481000
0#
#481500
1#
#482000
0#
#482500
1#
#483000
0#
#483500
1#
#484000
0#
#484500
1#
#485000
0#
#485500
1#
#486000
0#
#486500
1#
#487000
0#
#487500
1#
#488000
0#
#488500
1#
#489000
0#
#489500
1#
#490000
1(
0#
1&
#490500
0(
b10100 .
b1001 ,
0/
1#
#491000
0#
#491500
1#
#492000
0#
#492500
1#
#493000
0#
#493500
1#
#494000
0#
#494500
1#
#495000
0#
#495500
1#
#496000
0#
#496500
1#
#497000
0#
#497500
1#
#498000
0#
#498500
1#
#499000
0#
#499500
1#
#500000
0#
0&
#500500
1/
1#
#501000
0#
#501500
1#
#502000
0#
#502500
1#
#503000
0#
#503500
1#
#504000
0#
#504500
1#
#505000
0#
#505500
1#
#506000
0#
#506500
1#
#507000
0#
#507500
1#
#508000
0#
#508500
1#
#509000
0#
#509500
1#
#510000
1(
0#
1&
#510500
0(
b10110 .
b1010 ,
0/
1#
#511000
0#
#511500
1#
#512000
0#
#512500
1#
#513000
0#
#513500
1#
#514000
0#
#514500
1#
#515000
0#
#515500
1#
#516000
0#
#516500
1#
#517000
0#
#517500
1#
#518000
0#
#518500
1#
#519000
0#
#519500
1#
#520000
0#
0&
#520500
1/
1#
#521000
0#
#521500
1#
#522000
0#
#522500
1#
#523000
0#
#523500
1#
#524000
0#
#524500
1#
#525000
0#
#525500
1#
#526000
0#
#526500
1#
#527000
0#
#527500
1#
#528000
0#
#528500
1#
#529000
0#
#529500
1#
#530000
1(
0#
1&
#530500
0(
b11000 .
b1011 ,
0/
1#
#531000
0#
#531500
1#
#532000
0#
#532500
1#
#533000
0#
#533500
1#
#534000
0#
#534500
1#
#535000
0#
#535500
1#
#536000
0#
#536500
1#
#537000
0#
#537500
1#
#538000
0#
#538500
1#
#539000
0#
#539500
1#
#540000
0#
0&
#540500
1/
1#
#541000
0#
#541500
1#
#542000
0#
#542500
1#
#543000
0#
#543500
1#
#544000
0#
#544500
1#
#545000
0#
#545500
1#
#546000
0#
#546500
1#
#547000
0#
#547500
1#
#548000
0#
#548500
1#
#549000
0#
#549500
1#
#550000
1(
0#
1&
#550500
0(
b11010 .
b1100 ,
0/
1#
#551000
0#
#551500
1#
#552000
0#
#552500
1#
#553000
0#
#553500
1#
#554000
0#
#554500
1#
#555000
0#
#555500
1#
#556000
0#
#556500
1#
#557000
0#
#557500
1#
#558000
0#
#558500
1#
#559000
0#
#559500
1#
#560000
0#
0&
#560500
1/
1#
#561000
0#
#561500
1#
#562000
0#
#562500
1#
#563000
0#
#563500
1#
#564000
0#
#564500
1#
#565000
0#
#565500
1#
#566000
0#
#566500
1#
#567000
0#
#567500
1#
#568000
0#
#568500
1#
#569000
0#
#569500
1#
#570000
1(
0#
1&
#570500
0(
b11100 .
b1101 ,
0/
1#
#571000
0#
#571500
1#
#572000
0#
#572500
1#
#573000
0#
#573500
1#
#574000
0#
#574500
1#
#575000
0#
#575500
1#
#576000
0#
#576500
1#
#577000
0#
#577500
1#
#578000
0#
#578500
1#
#579000
0#
#579500
1#
#580000
0#
0&
#580500
1/
1#
#581000
0#
#581500
1#
#582000
0#
#582500
1#
#583000
0#
#583500
1#
#584000
0#
#584500
1#
#585000
0#
#585500
1#
#586000
0#
#586500
1#
#587000
0#
#587500
1#
#588000
0#
#588500
1#
#589000
0#
#589500
1#
#590000
1(
0#
1&
#590500
0(
b11110 .
b1110 ,
0/
1#
#591000
0#
#591500
1#
#592000
0#
#592500
1#
#593000
0#
#593500
1#
#594000
0#
#594500
1#
#595000
0#
#595500
1#
#596000
0#
#596500
1#
#597000
0#
#597500
1#
#598000
0#
#598500
1#
#599000
0#
#599500
1#
#600000
0#
0&
#600500
1/
1#
#601000
0#
#601500
1#
#602000
0#
#602500
1#
#603000
0#
#603500
1#
#604000
0#
#604500
1#
#605000
0#
#605500
1#
#606000
0#
#606500
1#
#607000
0#
#607500
1#
#608000
0#
#608500
1#
#609000
0#
#609500
1#
#610000
1(
0#
1&
#610500
0(
b100000 .
b1111 ,
0/
1#
#611000
0#
#611500
1#
#612000
0#
#612500
1#
#613000
0#
#613500
1#
#614000
0#
#614500
1#
#615000
0#
#615500
1#
#616000
0#
#616500
1#
#617000
0#
#617500
1#
#618000
0#
#618500
1#
#619000
0#
#619500
1#
#620000
0#
0&
#620500
1/
1#
#621000
0#
#621500
1#
#622000
0#
#622500
1#
#623000
0#
#623500
1#
#624000
0#
#624500
1#
#625000
0#
#625500
1#
#626000
0#
#626500
1#
#627000
0#
#627500
1#
#628000
0#
#628500
1#
#629000
0#
#629500
1#
#630000
1(
0#
1&
#630500
0(
1!
b100000 "
b100000 -
b10 .
b0 ,
0/
1#
#631000
0#
#631500
0!
1#
#632000
0#
#632500
1#
#633000
0#
#633500
1#
#634000
0#
#634500
1#
#635000
0#
#635500
1#
#636000
0#
#636500
1#
#637000
0#
#637500
1#
#638000
0#
#638500
1#
#639000
0#
#639500
1#
#640000
0#
0&
#640500
1/
1#
#641000
0#
#641500
1#
#642000
0#
#642500
1#
#643000
0#
#643500
1#
#644000
0#
#644500
1#
#645000
0#
#645500
1#
#646000
0#
#646500
1#
#647000
0#
#647500
1#
#648000
0#
#648500
1#
#649000
0#
#649500
1#
#650000
1(
0#
1&
#650500
0(
b100 .
b1 ,
0/
1#
#651000
0#
#651500
1#
#652000
0#
#652500
1#
#653000
0#
#653500
1#
#654000
0#
#654500
1#
#655000
0#
#655500
1#
#656000
0#
#656500
1#
#657000
0#
#657500
1#
#658000
0#
#658500
1#
#659000
0#
#659500
1#
#660000
0#
0&
#660500
1/
1#
#661000
0#
#661500
1#
#662000
0#
#662500
1#
#663000
0#
#663500
1#
#664000
0#
#664500
1#
#665000
0#
#665500
1#
#666000
0#
#666500
1#
#667000
0#
#667500
1#
#668000
0#
#668500
1#
#669000
0#
#669500
1#
#670000
1(
0#
1&
#670500
0(
b110 .
b10 ,
0/
1#
#671000
0#
#671500
1#
#672000
0#
#672500
1#
#673000
0#
#673500
1#
#674000
0#
#674500
1#
#675000
0#
#675500
1#
#676000
0#
#676500
1#
#677000
0#
#677500
1#
#678000
0#
#678500
1#
#679000
0#
#679500
1#
#680000
0#
0&
#680500
1/
1#
#681000
0#
#681500
1#
#682000
0#
#682500
1#
#683000
0#
#683500
1#
#684000
0#
#684500
1#
#685000
0#
#685500
1#
#686000
0#
#686500
1#
#687000
0#
#687500
1#
#688000
0#
#688500
1#
#689000
0#
#689500
1#
#690000
1(
0#
1&
#690500
0(
b1000 .
b11 ,
0/
1#
#691000
0#
#691500
1#
#692000
0#
#692500
1#
#693000
0#
#693500
1#
#694000
0#
#694500
1#
#695000
0#
#695500
1#
#696000
0#
#696500
1#
#697000
0#
#697500
1#
#698000
0#
#698500
1#
#699000
0#
#699500
1#
#700000
0#
0&
#700500
1/
1#
#701000
0#
#701500
1#
#702000
0#
#702500
1#
#703000
0#
#703500
1#
#704000
0#
#704500
1#
#705000
0#
#705500
1#
#706000
0#
#706500
1#
#707000
0#
#707500
1#
#708000
0#
#708500
1#
#709000
0#
#709500
1#
#710000
1(
0#
1&
#710500
0(
b1010 .
b100 ,
0/
1#
#711000
0#
#711500
1#
#712000
0#
#712500
1#
#713000
0#
#713500
1#
#714000
0#
#714500
1#
#715000
0#
#715500
1#
#716000
0#
#716500
1#
#717000
0#
#717500
1#
#718000
0#
#718500
1#
#719000
0#
#719500
1#
#720000
0#
0&
#720500
1/
1#
#721000
0#
#721500
1#
#722000
0#
#722500
1#
#723000
0#
#723500
1#
#724000
0#
#724500
1#
#725000
0#
#725500
1#
#726000
0#
#726500
1#
#727000
0#
#727500
1#
#728000
0#
#728500
1#
#729000
0#
#729500
1#
#730000
1(
0#
1&
#730500
0(
b1100 .
b101 ,
0/
1#
#731000
0#
#731500
1#
#732000
0#
#732500
1#
#733000
0#
#733500
1#
#734000
0#
#734500
1#
#735000
0#
#735500
1#
#736000
0#
#736500
1#
#737000
0#
#737500
1#
#738000
0#
#738500
1#
#739000
0#
#739500
1#
#740000
0#
0&
#740500
1/
1#
#741000
0#
#741500
1#
#742000
0#
#742500
1#
#743000
0#
#743500
1#
#744000
0#
#744500
1#
#745000
0#
#745500
1#
#746000
0#
#746500
1#
#747000
0#
#747500
1#
#748000
0#
#748500
1#
#749000
0#
#749500
1#
#750000
1(
0#
1&
#750500
0(
b1110 .
b110 ,
0/
1#
#751000
0#
#751500
1#
#752000
0#
#752500
1#
#753000
0#
#753500
1#
#754000
0#
#754500
1#
#755000
0#
#755500
1#
#756000
0#
#756500
1#
#757000
0#
#757500
1#
#758000
0#
#758500
1#
#759000
0#
#759500
1#
#760000
0#
0&
#760500
1/
1#
#761000
0#
#761500
1#
#762000
0#
#762500
1#
#763000
0#
#763500
1#
#764000
0#
#764500
1#
#765000
0#
#765500
1#
#766000
0#
#766500
1#
#767000
0#
#767500
1#
#768000
0#
#768500
1#
#769000
0#
#769500
1#
#770000
1(
0#
1&
#770500
0(
b10000 .
b111 ,
0/
1#
#771000
0#
#771500
1#
#772000
0#
#772500
1#
#773000
0#
#773500
1#
#774000
0#
#774500
1#
#775000
0#
#775500
1#
#776000
0#
#776500
1#
#777000
0#
#777500
1#
#778000
0#
#778500
1#
#779000
0#
#779500
1#
#780000
0#
0&
#780500
1/
1#
#781000
0#
#781500
1#
#782000
0#
#782500
1#
#783000
0#
#783500
1#
#784000
0#
#784500
1#
#785000
0#
#785500
1#
#786000
0#
#786500
1#
#787000
0#
#787500
1#
#788000
0#
#788500
1#
#789000
0#
#789500
1#
#790000
1(
0#
1&
#790500
0(
b10010 .
b1000 ,
0/
1#
#791000
0#
#791500
1#
#792000
0#
#792500
1#
#793000
0#
#793500
1#
#794000
0#
#794500
1#
#795000
0#
#795500
1#
#796000
0#
#796500
1#
#797000
0#
#797500
1#
#798000
0#
#798500
1#
#799000
0#
#799500
1#
#800000
0#
0&
#800500
1/
1#
#801000
0#
#801500
1#
#802000
0#
#802500
1#
#803000
0#
#803500
1#
#804000
0#
#804500
1#
#805000
0#
#805500
1#
#806000
0#
#806500
1#
#807000
0#
#807500
1#
#808000
0#
#808500
1#
#809000
0#
#809500
1#
#810000
1(
0#
1&
#810500
0(
b10100 .
b1001 ,
0/
1#
#811000
0#
#811500
1#
#812000
0#
#812500
1#
#813000
0#
#813500
1#
#814000
0#
#814500
1#
#815000
0#
#815500
1#
#816000
0#
#816500
1#
#817000
0#
#817500
1#
#818000
0#
#818500
1#
#819000
0#
#819500
1#
#820000
0#
0&
#820500
1/
1#
#821000
0#
#821500
1#
#822000
0#
#822500
1#
#823000
0#
#823500
1#
#824000
0#
#824500
1#
#825000
0#
#825500
1#
#826000
0#
#826500
1#
#827000
0#
#827500
1#
#828000
0#
#828500
1#
#829000
0#
#829500
1#
#830000
1(
0#
1&
#830500
0(
b10110 .
b1010 ,
0/
1#
#831000
0#
#831500
1#
#832000
0#
#832500
1#
#833000
0#
#833500
1#
#834000
0#
#834500
1#
#835000
0#
#835500
1#
#836000
0#
#836500
1#
#837000
0#
#837500
1#
#838000
0#
#838500
1#
#839000
0#
#839500
1#
#840000
0#
0&
#840500
1/
1#
#841000
0#
#841500
1#
#842000
0#
#842500
1#
#843000
0#
#843500
1#
#844000
0#
#844500
1#
#845000
0#
#845500
1#
#846000
0#
#846500
1#
#847000
0#
#847500
1#
#848000
0#
#848500
1#
#849000
0#
#849500
1#
#850000
1(
0#
1&
#850500
0(
b11000 .
b1011 ,
0/
1#
#851000
0#
#851500
1#
#852000
0#
#852500
1#
#853000
0#
#853500
1#
#854000
0#
#854500
1#
#855000
0#
